vdev_library/__init__.py
vdev_library/vn_phone_utils.py
vdev_library-0.0.3.dist-info/LICENSE
vdev_library-0.0.3.dist-info/METADATA
vdev_library-0.0.3.dist-info/WHEEL
vdev_library-0.0.3.dist-info/top_level.txt
vdev_library-0.0.3.dist-info/RECORD
